[
  {
    "line": 2,
    "elements": [
      {
        "start_timestamp": "2020-02-24T05:27:25.301Z",
        "line": 4,
        "name": "Successul Registration",
        "description": "",
        "id": "testmeapp-registration;successul-registration",
        "type": "scenario",
        "keyword": "Scenario",
        "steps": [
          {
            "result": {
              "duration": 36447233200,
              "status": "passed"
            },
            "line": 5,
            "name": "User clicks on signup button",
            "match": {
              "location": "Register.user_clicks_on_signup_button()"
            },
            "keyword": "Given "
          },
          {
            "result": {
              "duration": 128357300,
              "status": "passed"
            },
            "line": 6,
            "name": "enters username as \"naren4567\"",
            "match": {
              "arguments": [
                {
                  "val": "\"naren4567\"",
                  "offset": 19
                }
              ],
              "location": "Register.enters_username_as(String)"
            },
            "keyword": "And "
          },
          {
            "result": {
              "duration": 115627200,
              "status": "passed"
            },
            "line": 7,
            "name": "enters first name as \"naren\"",
            "match": {
              "arguments": [
                {
                  "val": "\"naren\"",
                  "offset": 21
                }
              ],
              "location": "Register.enters_first_name_as(String)"
            },
            "keyword": "And "
          },
          {
            "result": {
              "duration": 146789000,
              "status": "passed"
            },
            "line": 8,
            "name": "enters last name as \"dran\"",
            "match": {
              "arguments": [
                {
                  "val": "\"dran\"",
                  "offset": 20
                }
              ],
              "location": "Register.enters_last_name_as(String)"
            },
            "keyword": "And "
          },
          {
            "result": {
              "duration": 120200900,
              "status": "passed"
            },
            "line": 9,
            "name": "enters password as \"naren123\"",
            "match": {
              "arguments": [
                {
                  "val": "\"naren123\"",
                  "offset": 19
                }
              ],
              "location": "Register.enters_password_as(String)"
            },
            "keyword": "And "
          },
          {
            "result": {
              "duration": 112441800,
              "status": "passed"
            },
            "line": 10,
            "name": "enters confirm password as \"naren123\"",
            "match": {
              "arguments": [
                {
                  "val": "\"naren123\"",
                  "offset": 27
                }
              ],
              "location": "Register.enters_confirm_password_as(String)"
            },
            "keyword": "And "
          },
          {
            "result": {
              "duration": 89441700,
              "status": "passed"
            },
            "line": 11,
            "name": "clicks on gender male radio button",
            "match": {
              "location": "Register.clicks_on_gender_male_radio_button()"
            },
            "keyword": "And "
          },
          {
            "result": {
              "duration": 202139400,
              "status": "passed"
            },
            "line": 12,
            "name": "enters email as \"tsri@gmail.com\"",
            "match": {
              "arguments": [
                {
                  "val": "\"tsri@gmail.com\"",
                  "offset": 16
                }
              ],
              "location": "Register.enters_email_as(String)"
            },
            "keyword": "And "
          },
          {
            "result": {
              "duration": 162090900,
              "status": "passed"
            },
            "line": 13,
            "name": "enters mobile number as {12345678}",
            "match": {
              "arguments": [
                {
                  "val": "{12345678}",
                  "offset": 24
                }
              ],
              "location": "Register.enters_mobileno_as(String)"
            },
            "keyword": "And "
          },
          {
            "result": {
              "duration": 261251300,
              "status": "passed"
            },
            "line": 14,
            "name": "enters dob as \"1-2-2022\"",
            "match": {
              "arguments": [
                {
                  "val": "\"1-2-2022\"",
                  "offset": 14
                }
              ],
              "location": "Register.enters_dob_as(String)"
            },
            "keyword": "And "
          },
          {
            "result": {
              "duration": 188979900,
              "status": "passed"
            },
            "line": 15,
            "name": "enters address as \"coimbatore\"",
            "match": {
              "arguments": [
                {
                  "val": "\"coimbatore\"",
                  "offset": 18
                }
              ],
              "location": "Register.enters_address_as(String)"
            },
            "keyword": "And "
          },
          {
            "result": {
              "duration": 228202800,
              "status": "passed"
            },
            "line": 16,
            "name": "selects security question clicks",
            "match": {
              "location": "Register.selects_security_question_clicks()"
            },
            "keyword": "And "
          },
          {
            "result": {
              "duration": 170199600,
              "status": "passed"
            },
            "line": 17,
            "name": "enters answer as \"blue\"",
            "match": {
              "arguments": [
                {
                  "val": "\"blue\"",
                  "offset": 17
                }
              ],
              "location": "Register.enters_answer_as(String)"
            },
            "keyword": "And "
          },
          {
            "result": {
              "duration": 1239670000,
              "status": "passed"
            },
            "line": 18,
            "name": "click on register button",
            "match": {
              "location": "Register.click_on_register_button()"
            },
            "keyword": "When "
          },
          {
            "result": {
              "duration": 12763900,
              "status": "passed"
            },
            "line": 19,
            "name": "welcome page is displayed",
            "match": {
              "location": "Register.welcome_page_is_displayed()"
            },
            "keyword": "Then "
          }
        ]
      }
    ],
    "name": "TestMeApp Registration",
    "description": "",
    "id": "testmeapp-registration",
    "keyword": "Feature",
    "uri": "classpath:p1/Register.feature",
    "tags": []
  }
]